cluster_experiment_utils/__init__.py
cluster_experiment_utils/flowcept_utils.py
cluster_experiment_utils/utils.py
cluster_experiment_utils/version.py
cluster_experiment_utils/cluster_utils/__init__.py
cluster_experiment_utils/cluster_utils/base_cluster_utils.py
cluster_experiment_utils/cluster_utils/lsf_utils.py
cluster_experiment_utils/cluster_utils/slurm_utils.py
tests/__init__.py
tests/test_the_utils.py
cluster_experiment_utils-0.0.20.dist-info/METADATA
cluster_experiment_utils-0.0.20.dist-info/WHEEL
cluster_experiment_utils-0.0.20.dist-info/top_level.txt
cluster_experiment_utils-0.0.20.dist-info/RECORD
