Metadata-Version: 2.1
Name: cluster_experiment_utils
Version: 0.0.20
Summary: Cluster Experiment Utils
Home-page: https://github.com/renan-souza/experiment_utils
Author: Renan Souza
Author-email: contact@renansouza.org
License: MIT
Keywords: experiment-utils,experiment_utils
Classifier: License :: OSI Approved :: MIT License
Classifier: Operating System :: OS Independent
Classifier: Programming Language :: Python :: 3.8
Classifier: Programming Language :: Python :: 3.9
Classifier: Programming Language :: Python :: 3.10
Classifier: Intended Audience :: Developers
Classifier: Intended Audience :: Science/Research
Classifier: Natural Language :: English
Classifier: Topic :: System :: Distributed Computing
Classifier: Topic :: Scientific/Engineering
Classifier: Topic :: Scientific/Engineering :: Artificial Intelligence
Classifier: Topic :: Scientific/Engineering :: Information Analysis
Classifier: Topic :: System :: Logging
Classifier: Topic :: System :: Monitoring
Classifier: Topic :: Database
Requires-Python: >=3.8
Requires-Dist: pymongo ==4.3.3
Requires-Dist: flowcept[analytcs]
Requires-Dist: black ==23.1.0
Requires-Dist: omegaconf
Requires-Dist: psij-python
